Swagger2Tests/__init__.py
Swagger2Tests/run.py
Swagger2Tests/utils.py
Swagger2Tests/constants/__init__.py
Swagger2Tests/constants/base_constants.py
Swagger2Tests/helpers/__init__.py
Swagger2Tests/helpers/helper.py
Swagger2Tests/parse/Swagger2Tests.py
Swagger2Tests/parse/__init__.py
Swagger2Tests/templates/pytestcase.tpl
apps/__init__.py
apps/constants/__init__.py
apps/constants/base_constants.py
apps/helpers/__init__.py
apps/helpers/helper.py
apps/templates/pytestcase.tpl
tests/__init__.py
tests/test_run.py
Swagger2Tests-1.2.2.dist-info/METADATA
Swagger2Tests-1.2.2.dist-info/WHEEL
Swagger2Tests-1.2.2.dist-info/entry_points.txt
Swagger2Tests-1.2.2.dist-info/top_level.txt
Swagger2Tests-1.2.2.dist-info/RECORD
