Metadata-Version: 2.1
Name: Swagger2Tests
Version: 1.2.2
Summary: swagger
Home-page: https://gitee.com/visonforcoding/code-template-tools
Author: visonforcoding
Author-email: visonforcoding@gmail.com
License: UNKNOWN
Platform: UNKNOWN
Classifier: Programming Language :: Python :: 3
Classifier: License :: OSI Approved :: MIT License
Classifier: Operating System :: OS Independent
Requires-Dist: argparse
Requires-Dist: jinja2
Requires-Dist: pytest
Requires-Dist: requests
Requires-Dist: coloredlogs
Requires-Dist: Faker
Requires-Dist: Werkzeug
